botaistv/__init__.py
botaistv/cli.py
botaistv/core.py
botaistv-1.0.0.dist-info/METADATA
botaistv-1.0.0.dist-info/WHEEL
botaistv-1.0.0.dist-info/entry_points.txt
botaistv-1.0.0.dist-info/top_level.txt
botaistv-1.0.0.dist-info/RECORD
