Metadata-Version: 2.4
Name: botaistv
Version: 1.0.0
Summary: STV AI Chatbot Library for Python
Home-page: https://github.com/phuctrong1tuv
Author: Trọng Phúc
Author-email: phuctrongytb16@gmail.com
Project-URL: TikTok, https://vm.tiktok.com/@aistvchat
Project-URL: GitHub, https://github.com/phuctrong1tuv
Keywords: chatbot ai stv termux
Classifier: Programming Language :: Python :: 3
Classifier: License :: OSI Approved :: MIT License
Classifier: Operating System :: OS Independent
Requires-Python: >=3.8
Requires-Dist: requests
Dynamic: author
Dynamic: author-email
Dynamic: classifier
Dynamic: description
Dynamic: description-content-type
Dynamic: home-page
Dynamic: keywords
Dynamic: project-url
Dynamic: requires-dist
Dynamic: requires-python
Dynamic: summary
